mattuni.py
mattuni-0.5.4.dist-info/METADATA
mattuni-0.5.4.dist-info/WHEEL
mattuni-0.5.4.dist-info/top_level.txt
mattuni-0.5.4.dist-info/RECORD
