Metadata-Version: 2.1
Name: mattuni
Version: 0.5.4
Summary: Coding challenges
Author-email: Matt Groth <mjgroth@mit.edu>
Requires-Dist: requests
Requires-Dist: mstuff (==0.7.2)
